collective.volto.formsupport-3.3.0-py3.10-nspkg.pth
collective/volto/formsupport/__init__.py
collective/volto/formsupport/configure.zcml
collective/volto/formsupport/interfaces.py
collective/volto/formsupport/permissions.zcml
collective/volto/formsupport/setuphandlers.py
collective/volto/formsupport/testing.py
collective/volto/formsupport/upgrades.py
collective/volto/formsupport/upgrades.zcml
collective/volto/formsupport/utils.py
collective/volto/formsupport/adapters/__init__.py
collective/volto/formsupport/adapters/configure.zcml
collective/volto/formsupport/adapters/post.py
collective/volto/formsupport/browser/__init__.py
collective/volto/formsupport/browser/configure.zcml
collective/volto/formsupport/browser/saved_data.py
collective/volto/formsupport/browser/send_mail_template.pt
collective/volto/formsupport/browser/send_mail_template_table.pt
collective/volto/formsupport/browser/overrides/.gitkeep
collective/volto/formsupport/browser/static/.gitkeep
collective/volto/formsupport/captcha/__init__.py
collective/volto/formsupport/captcha/configure.zcml
collective/volto/formsupport/captcha/hcaptcha.py
collective/volto/formsupport/captcha/honeypot.py
collective/volto/formsupport/captcha/norobots.py
collective/volto/formsupport/captcha/recaptcha.py
collective/volto/formsupport/captcha/vocabularies.py
collective/volto/formsupport/datamanager/__init__.py
collective/volto/formsupport/datamanager/catalog.py
collective/volto/formsupport/datamanager/configure.zcml
collective/volto/formsupport/events/__init__.py
collective/volto/formsupport/locales/README.rst
collective/volto/formsupport/locales/__init__.py
collective/volto/formsupport/locales/collective.volto.formsupport.pot
collective/volto/formsupport/locales/update.py
collective/volto/formsupport/locales/update.sh
collective/volto/formsupport/locales/de/LC_MESSAGES/collective.volto.formsupport.mo
collective/volto/formsupport/locales/de/LC_MESSAGES/collective.volto.formsupport.po
collective.volto.formsupport-3.3.0.dist-info/LICENSE.GPL
collective.volto.formsupport-3.3.0.dist-info/LICENSE.rst
collective.volto.formsupport-3.3.0.dist-info/METADATA
collective.volto.formsupport-3.3.0.dist-info/WHEEL
collective.volto.formsupport-3.3.0.dist-info/entry_points.txt
collective.volto.formsupport-3.3.0.dist-info/namespace_packages.txt
collective.volto.formsupport-3.3.0.dist-info/top_level.txt
collective.volto.formsupport-3.3.0.dist-info/RECORD
