Metadata-Version: 2.1
Name: collective.volto.formsupport
Version: 3.3.0
Summary: Add support for customizable forms in Volto
Home-page: https://github.com/collective/collective.volto.formsupport
Author: RedTurtle Technology
Author-email: sviluppo@redturtle.it
License: GPL version 2
Project-URL: PyPI, https://pypi.python.org/pypi/collective.volto.formsupport
Project-URL: Source, https://github.com/collective/collective.volto.formsupport
Project-URL: Tracker, https://github.com/collective/collective.volto.formsupport/issues
Keywords: Python Plone CMS
Classifier: Development Status :: 5 - Production/Stable
Classifier: Environment :: Web Environment
Classifier: Framework :: Plone
Classifier: Framework :: Plone :: Addon
Classifier: Framework :: Plone :: 5.2
Classifier: Framework :: Plone :: 6.0
Classifier: Programming Language :: Python
Classifier: Programming Language :: Python :: 3.8
Classifier: Programming Language :: Python :: 3.9
Classifier: Programming Language :: Python :: 3.10
Classifier: Programming Language :: Python :: 3.11
Classifier: Operating System :: OS Independent
Classifier: License :: OSI Approved :: GNU General Public License v2 (GPLv2)
Requires-Python: >=3.8
License-File: LICENSE.GPL
License-File: LICENSE.rst
Requires-Dist: setuptools
Requires-Dist: z3c.jbot
Requires-Dist: Zope
Requires-Dist: plone.api >=1.8.4
Requires-Dist: plone.dexterity
Requires-Dist: plone.i18n
Requires-Dist: plone.memoize
Requires-Dist: plone.namedfile
Requires-Dist: plone.protect
Requires-Dist: plone.registry
Requires-Dist: plone.restapi >=8.36.0
Requires-Dist: plone.schema
Requires-Dist: Products.GenericSetup
Requires-Dist: Products.PortalTransforms
Requires-Dist: souper.plone
Requires-Dist: click
Requires-Dist: beautifulsoup4
Requires-Dist: collective.volto.otp
Provides-Extra: blocksfield
Requires-Dist: collective.volto.blocksfield ; extra == 'blocksfield'
Provides-Extra: hcaptcha
Requires-Dist: plone.formwidget.hcaptcha >=1.0.1 ; extra == 'hcaptcha'
Provides-Extra: honeypot
Requires-Dist: collective.honeypot >=2.1 ; extra == 'honeypot'
Provides-Extra: norobots
Requires-Dist: collective.z3cform.norobots ; extra == 'norobots'
Provides-Extra: recaptcha
Requires-Dist: plone.formwidget.recaptcha ; extra == 'recaptcha'
Provides-Extra: test
Requires-Dist: plone.app.testing ; extra == 'test'
Requires-Dist: plone.testing >=5.0.0 ; extra == 'test'
Requires-Dist: plone.app.contenttypes[test] ; extra == 'test'
Requires-Dist: plone.restapi[test] ; extra == 'test'
Requires-Dist: plone.app.iterate ; extra == 'test'
Requires-Dist: Products.MailHost ; extra == 'test'
Requires-Dist: plone.browserlayer ; extra == 'test'
Requires-Dist: collective.MockMailHost ; extra == 'test'
Requires-Dist: collective.honeypot ; extra == 'test'
Requires-Dist: plone.formwidget.hcaptcha ; extra == 'test'
Requires-Dist: plone.formwidget.recaptcha ; extra == 'test'
Requires-Dist: collective.z3cform.norobots ; extra == 'test'
Requires-Dist: collective.volto.otp ; extra == 'test'
